{
  "activerecord": {
    "mean": 105.05415093349784,
    "rsd_pct": 0.5640622909437454,
    "micro": false
  },
  "hexapdf": {
    "mean": 2452.4000075956187,
    "rsd_pct": 0.9719146029960021,
    "micro": false
  },
  "liquid-render": {
    "mean": 127.05412348079834,
    "rsd_pct": 1.7510978510692772,
    "micro": false
  },
  "mail": {
    "mean": 156.1953641298249,
    "rsd_pct": 0.16105391191069177,
    "micro": false
  },
  "psych-load": {
    "mean": 1956.5570573012035,
    "rsd_pct": 0.031859573078467714,
    "micro": false
  },
  "railsbench": {
    "mean": 2086.2233785291514,
    "rsd_pct": 0.9115231648653734,
    "micro": false
  },
  "binarytrees": {
    "mean": 370.13838942798355,
    "rsd_pct": 0.09338314804843377,
    "micro": false
  },
  "chunky_png": {
    "mean": 654.4130869209766,
    "rsd_pct": 0.04400698870774536,
    "micro": false
  },
  "erubi": {
    "mean": 327.69750729203224,
    "rsd_pct": 0.7897600961327919,
    "micro": false
  },
  "erubi_rails": {
    "mean": 19.491563927772294,
    "rsd_pct": 3.400184196515406,
    "micro": false
  },
  "fannkuchredux": {
    "mean": 2340.170948455731,
    "rsd_pct": 0.21958777324600653,
    "micro": false
  },
  "lee": {
    "mean": 967.2676384449005,
    "rsd_pct": 1.7986290349449796,
    "micro": false
  },
  "nbody": {
    "mean": 89.53593553831944,
    "rsd_pct": 0.08692016297788342,
    "micro": false
  },
  "optcarrot": {
    "mean": 3451.3296753168106,
    "rsd_pct": 0.6056062631905773,
    "micro": false
  },
  "rubykon": {
    "mean": 6852.456289778153,
    "rsd_pct": 0.6758556455989102,
    "micro": false
  },
  "30k_ifelse": {
    "mean": 359.56130316480994,
    "rsd_pct": 0.07565911837524666,
    "micro": true
  },
  "30k_methods": {
    "mean": 870.0694658539512,
    "rsd_pct": 0.018917253512804183,
    "micro": true
  },
  "cfunc_itself": {
    "mean": 48.674511041156855,
    "rsd_pct": 0.8250320291866436,
    "micro": true
  },
  "fib": {
    "mean": 63.340928157170616,
    "rsd_pct": 0.050948922222101754,
    "micro": true
  },
  "getivar": {
    "mean": 44.22965842106986,
    "rsd_pct": 0.10301174794938402,
    "micro": true
  },
  "keyword_args": {
    "mean": 54.719152397226765,
    "rsd_pct": 0.25110657474292875,
    "micro": true
  },
  "respond_to": {
    "mean": 192.0620115975348,
    "rsd_pct": 0.15444008543503296,
    "micro": true
  },
  "setivar": {
    "mean": 41.03066869682134,
    "rsd_pct": 0.25520998022594826,
    "micro": true
  },
  "str_concat": {
    "mean": 45.10521901233884,
    "rsd_pct": 1.5139741193771021,
    "micro": true
  }
}