{
  "activerecord": {
    "mean": 110.09301162885697,
    "rsd_pct": 0.4840445751910791,
    "micro": false
  },
  "hexapdf": {
    "mean": 2461.499823195239,
    "rsd_pct": 1.4686545328561953,
    "micro": false
  },
  "liquid-render": {
    "mean": 127.93738940635171,
    "rsd_pct": 1.730096544097855,
    "micro": false
  },
  "mail": {
    "mean": 164.84286154552203,
    "rsd_pct": 0.3785456773332701,
    "micro": false
  },
  "psych-load": {
    "mean": 1936.4364648858707,
    "rsd_pct": 0.1449097623912129,
    "micro": false
  },
  "railsbench": {
    "mean": 2171.6327557961145,
    "rsd_pct": 1.5876266994326993,
    "micro": false
  },
  "binarytrees": {
    "mean": 367.8978186362656,
    "rsd_pct": 1.3858543535322214,
    "micro": false
  },
  "chunky_png": {
    "mean": 658.1756833940744,
    "rsd_pct": 0.10503114474826374,
    "micro": false
  },
  "discourse": {
    "mean": 496.23530850005454,
    "rsd_pct": 9.696986043118956,
    "micro": false
  },
  "erubi": {
    "mean": 422.5823562790422,
    "rsd_pct": 0.7997258914484695,
    "micro": false
  },
  "erubi_rails": {
    "mean": 20.32827812583182,
    "rsd_pct": 3.227110203288743,
    "micro": false
  },
  "fannkuchredux": {
    "mean": 7028.740811347961,
    "rsd_pct": 0.09170719855500378,
    "micro": false
  },
  "lee": {
    "mean": 911.6562978279861,
    "rsd_pct": 0.2459120945083475,
    "micro": false
  },
  "nbody": {
    "mean": 88.81636983630332,
    "rsd_pct": 0.4934277616599796,
    "micro": false
  },
  "optcarrot": {
    "mean": 3460.6440561513105,
    "rsd_pct": 0.5961572165252428,
    "micro": false
  },
  "rubykon": {
    "mean": 7893.962187568347,
    "rsd_pct": 0.7004961823354915,
    "micro": false
  },
  "30k_ifelse": {
    "mean": 358.29855606637216,
    "rsd_pct": 0.1678861818830085,
    "micro": true
  },
  "30k_methods": {
    "mean": 882.6466355980797,
    "rsd_pct": 0.05920988484358799,
    "micro": true
  },
  "cfunc_itself": {
    "mean": 47.06521070219647,
    "rsd_pct": 0.8704051450735776,
    "micro": true
  },
  "fib": {
    "mean": 62.48828758511891,
    "rsd_pct": 0.6045937542258616,
    "micro": true
  },
  "getivar": {
    "mean": 42.55305071048506,
    "rsd_pct": 0.7037221355116471,
    "micro": true
  },
  "keyword_args": {
    "mean": 53.53540638881669,
    "rsd_pct": 0.8440685202027756,
    "micro": true
  },
  "respond_to": {
    "mean": 184.72507992045624,
    "rsd_pct": 0.3934932447196378,
    "micro": true
  },
  "setivar": {
    "mean": 49.753110492910515,
    "rsd_pct": 0.798201920118782,
    "micro": true
  }
}