{
  "activerecord": {
    "mean": 109.55245890304704,
    "rsd_pct": 1.042196653638614,
    "micro": false
  },
  "hexapdf": {
    "mean": 2177.206852566451,
    "rsd_pct": 0.6523178628091801,
    "micro": false
  },
  "jekyll": {
    "mean": 7394.0805164165795,
    "rsd_pct": 2.1047550660592775,
    "micro": false
  },
  "liquid-render": {
    "mean": 119.78902956055607,
    "rsd_pct": 2.445758481996507,
    "micro": false
  },
  "mail": {
    "mean": 145.34098184190867,
    "rsd_pct": 0.9819172583196868,
    "micro": false
  },
  "psych-load": {
    "mean": 1762.0327998884022,
    "rsd_pct": 1.9254533002389622,
    "micro": false
  },
  "railsbench": {
    "mean": 2383.2781980745494,
    "rsd_pct": 1.7296608781114067,
    "micro": false
  },
  "binarytrees": {
    "mean": 281.3608099355317,
    "rsd_pct": 0.6326082595691742,
    "micro": false
  },
  "fannkuchredux": {
    "mean": 5335.957049392164,
    "rsd_pct": 0.02149967354684842,
    "micro": false
  },
  "lee": {
    "mean": 805.6971811378995,
    "rsd_pct": 1.2845463709022589,
    "micro": false
  },
  "nbody": {
    "mean": 72.27897928671891,
    "rsd_pct": 0.06769832187929224,
    "micro": false
  },
  "optcarrot": {
    "mean": 3181.0181031934917,
    "rsd_pct": 0.6025496755125419,
    "micro": false
  },
  "rubykon": {
    "mean": 5495.016590133309,
    "rsd_pct": 1.2384095866870706,
    "micro": false
  },
  "30k_ifelse": {
    "mean": 323.1435745882873,
    "rsd_pct": 0.15997342383177793,
    "micro": true
  },
  "30k_methods": {
    "mean": 754.3663675075068,
    "rsd_pct": 0.045247484219864506,
    "micro": true
  },
  "cfunc_itself": {
    "mean": 38.807706784074135,
    "rsd_pct": 0.2884561724006929,
    "micro": true
  },
  "fib": {
    "mean": 52.03194639583429,
    "rsd_pct": 0.06798697046919751,
    "micro": true
  },
  "getivar": {
    "mean": 36.2612891994979,
    "rsd_pct": 0.09545685864304865,
    "micro": true
  },
  "keyword_args": {
    "mean": 45.56615580533282,
    "rsd_pct": 0.10972640974686232,
    "micro": true
  },
  "respond_to": {
    "mean": 155.47796744978479,
    "rsd_pct": 0.40396468610331154,
    "micro": true
  },
  "setivar": {
    "mean": 44.227583074440425,
    "rsd_pct": 0.13065937805017722,
    "micro": true
  }
}