{
  "aarch64_prod_ruby_no_jit": {
    "erubi_rails": {
      "warmup_itrs": 5,
      "min_bench_itrs": 971,
      "min_bench_time": 0,
      "estimated_time": 0
    },
    "fib": {
      "warmup_itrs": 5,
      "min_bench_itrs": 313,
      "min_bench_time": 0,
      "estimated_time": 0
    },
    "hexapdf": {
      "warmup_itrs": 5,
      "min_bench_itrs": 15,
      "min_bench_time": 0,
      "estimated_time": 0
    },
    "rubykon": {
      "warmup_itrs": 5,
      "min_bench_itrs": 15,
      "min_bench_time": 0,
      "estimated_time": 0
    },
    "binarytrees": {
      "warmup_itrs": 5,
      "min_bench_itrs": 68,
      "min_bench_time": 0,
      "estimated_time": 0
    },
    "psych-load": {
      "warmup_itrs": 5,
      "min_bench_itrs": 15,
      "min_bench_time": 0,
      "estimated_time": 0
    },
    "30k_ifelse": {
      "warmup_itrs": 5,
      "min_bench_itrs": 55,
      "min_bench_time": 0,
      "estimated_time": 0
    },
    "lee": {
      "warmup_itrs": 5,
      "min_bench_itrs": 22,
      "min_bench_time": 0,
      "estimated_time": 0
    },
    "mail": {
      "warmup_itrs": 5,
      "min_bench_itrs": 123,
      "min_bench_time": 0,
      "estimated_time": 0
    },
    "30k_methods": {
      "warmup_itrs": 5,
      "min_bench_itrs": 22,
      "min_bench_time": 0,
      "estimated_time": 0
    },
    "cfunc_itself": {
      "warmup_itrs": 5,
      "min_bench_itrs": 446,
      "min_bench_time": 0,
      "estimated_time": 0
    },
    "railsbench": {
      "warmup_itrs": 5,
      "min_bench_itrs": 15,
      "min_bench_time": 0,
      "estimated_time": 0
    },
    "liquid-render": {
      "warmup_itrs": 5,
      "min_bench_itrs": 155,
      "min_bench_time": 0,
      "estimated_time": 0
    },
    "keyword_args": {
      "warmup_itrs": 5,
      "min_bench_itrs": 379,
      "min_bench_time": 0,
      "estimated_time": 0
    },
    "respond_to": {
      "warmup_itrs": 5,
      "min_bench_itrs": 101,
      "min_bench_time": 0,
      "estimated_time": 0
    },
    "activerecord": {
      "warmup_itrs": 5,
      "min_bench_itrs": 182,
      "min_bench_time": 0,
      "estimated_time": 0
    },
    "fannkuchredux": {
      "warmup_itrs": 5,
      "min_bench_itrs": 15,
      "min_bench_time": 0,
      "estimated_time": 0
    },
    "optcarrot": {
      "warmup_itrs": 5,
      "min_bench_itrs": 15,
      "min_bench_time": 0,
      "estimated_time": 0
    },
    "getivar": {
      "warmup_itrs": 5,
      "min_bench_itrs": 802,
      "min_bench_time": 0,
      "estimated_time": 0
    },
    "discourse": {
      "warmup_itrs": 5,
      "min_bench_itrs": 35,
      "min_bench_time": 0,
      "estimated_time": 0
    },
    "chunky_png": {
      "warmup_itrs": 5,
      "min_bench_itrs": 29,
      "min_bench_time": 0,
      "estimated_time": 0
    },
    "nbody": {
      "warmup_itrs": 5,
      "min_bench_itrs": 284,
      "min_bench_time": 0,
      "estimated_time": 0
    },
    "setivar": {
      "warmup_itrs": 5,
      "min_bench_itrs": 1900,
      "min_bench_time": 0,
      "estimated_time": 0
    },
    "erubi": {
      "warmup_itrs": 5,
      "min_bench_itrs": 48,
      "min_bench_time": 0,
      "estimated_time": 0
    }
  },
  "aarch64_prod_ruby_with_yjit": {
    "erubi_rails": {
      "warmup_itrs": 20,
      "min_bench_itrs": 971,
      "min_bench_time": 0,
      "estimated_time": 0
    },
    "fib": {
      "warmup_itrs": 20,
      "min_bench_itrs": 313,
      "min_bench_time": 0,
      "estimated_time": 0
    },
    "hexapdf": {
      "warmup_itrs": 20,
      "min_bench_itrs": 15,
      "min_bench_time": 0,
      "estimated_time": 0
    },
    "rubykon": {
      "warmup_itrs": 20,
      "min_bench_itrs": 15,
      "min_bench_time": 0,
      "estimated_time": 0
    },
    "binarytrees": {
      "warmup_itrs": 20,
      "min_bench_itrs": 68,
      "min_bench_time": 0,
      "estimated_time": 0
    },
    "psych-load": {
      "warmup_itrs": 20,
      "min_bench_itrs": 15,
      "min_bench_time": 0,
      "estimated_time": 0
    },
    "30k_ifelse": {
      "warmup_itrs": 20,
      "min_bench_itrs": 55,
      "min_bench_time": 0,
      "estimated_time": 0
    },
    "lee": {
      "warmup_itrs": 20,
      "min_bench_itrs": 22,
      "min_bench_time": 0,
      "estimated_time": 0
    },
    "mail": {
      "warmup_itrs": 20,
      "min_bench_itrs": 123,
      "min_bench_time": 0,
      "estimated_time": 0
    },
    "30k_methods": {
      "warmup_itrs": 20,
      "min_bench_itrs": 22,
      "min_bench_time": 0,
      "estimated_time": 0
    },
    "cfunc_itself": {
      "warmup_itrs": 20,
      "min_bench_itrs": 446,
      "min_bench_time": 0,
      "estimated_time": 0
    },
    "railsbench": {
      "warmup_itrs": 20,
      "min_bench_itrs": 15,
      "min_bench_time": 0,
      "estimated_time": 0
    },
    "liquid-render": {
      "warmup_itrs": 20,
      "min_bench_itrs": 155,
      "min_bench_time": 0,
      "estimated_time": 0
    },
    "keyword_args": {
      "warmup_itrs": 20,
      "min_bench_itrs": 379,
      "min_bench_time": 0,
      "estimated_time": 0
    },
    "respond_to": {
      "warmup_itrs": 20,
      "min_bench_itrs": 101,
      "min_bench_time": 0,
      "estimated_time": 0
    },
    "activerecord": {
      "warmup_itrs": 20,
      "min_bench_itrs": 182,
      "min_bench_time": 0,
      "estimated_time": 0
    },
    "fannkuchredux": {
      "warmup_itrs": 20,
      "min_bench_itrs": 15,
      "min_bench_time": 0,
      "estimated_time": 0
    },
    "optcarrot": {
      "warmup_itrs": 20,
      "min_bench_itrs": 15,
      "min_bench_time": 0,
      "estimated_time": 0
    },
    "getivar": {
      "warmup_itrs": 20,
      "min_bench_itrs": 802,
      "min_bench_time": 0,
      "estimated_time": 0
    },
    "discourse": {
      "warmup_itrs": 20,
      "min_bench_itrs": 35,
      "min_bench_time": 0,
      "estimated_time": 0
    },
    "chunky_png": {
      "warmup_itrs": 20,
      "min_bench_itrs": 29,
      "min_bench_time": 0,
      "estimated_time": 0
    },
    "nbody": {
      "warmup_itrs": 20,
      "min_bench_itrs": 284,
      "min_bench_time": 0,
      "estimated_time": 0
    },
    "setivar": {
      "warmup_itrs": 20,
      "min_bench_itrs": 1900,
      "min_bench_time": 0,
      "estimated_time": 0
    },
    "erubi": {
      "warmup_itrs": 20,
      "min_bench_itrs": 48,
      "min_bench_time": 0,
      "estimated_time": 0
    }
  },
  "aarch64_yjit_stats": {
    "erubi_rails": {
      "warmup_itrs": 20,
      "min_bench_itrs": 971,
      "min_bench_time": 0,
      "estimated_time": 0
    },
    "fib": {
      "warmup_itrs": 20,
      "min_bench_itrs": 313,
      "min_bench_time": 0,
      "estimated_time": 0
    },
    "hexapdf": {
      "warmup_itrs": 20,
      "min_bench_itrs": 15,
      "min_bench_time": 0,
      "estimated_time": 0
    },
    "rubykon": {
      "warmup_itrs": 20,
      "min_bench_itrs": 15,
      "min_bench_time": 0,
      "estimated_time": 0
    },
    "binarytrees": {
      "warmup_itrs": 20,
      "min_bench_itrs": 68,
      "min_bench_time": 0,
      "estimated_time": 0
    },
    "psych-load": {
      "warmup_itrs": 20,
      "min_bench_itrs": 15,
      "min_bench_time": 0,
      "estimated_time": 0
    },
    "30k_ifelse": {
      "warmup_itrs": 20,
      "min_bench_itrs": 55,
      "min_bench_time": 0,
      "estimated_time": 0
    },
    "lee": {
      "warmup_itrs": 20,
      "min_bench_itrs": 22,
      "min_bench_time": 0,
      "estimated_time": 0
    },
    "mail": {
      "warmup_itrs": 20,
      "min_bench_itrs": 123,
      "min_bench_time": 0,
      "estimated_time": 0
    },
    "30k_methods": {
      "warmup_itrs": 20,
      "min_bench_itrs": 22,
      "min_bench_time": 0,
      "estimated_time": 0
    },
    "cfunc_itself": {
      "warmup_itrs": 20,
      "min_bench_itrs": 446,
      "min_bench_time": 0,
      "estimated_time": 0
    },
    "railsbench": {
      "warmup_itrs": 20,
      "min_bench_itrs": 15,
      "min_bench_time": 0,
      "estimated_time": 0
    },
    "liquid-render": {
      "warmup_itrs": 20,
      "min_bench_itrs": 155,
      "min_bench_time": 0,
      "estimated_time": 0
    },
    "keyword_args": {
      "warmup_itrs": 20,
      "min_bench_itrs": 379,
      "min_bench_time": 0,
      "estimated_time": 0
    },
    "respond_to": {
      "warmup_itrs": 20,
      "min_bench_itrs": 101,
      "min_bench_time": 0,
      "estimated_time": 0
    },
    "activerecord": {
      "warmup_itrs": 20,
      "min_bench_itrs": 182,
      "min_bench_time": 0,
      "estimated_time": 0
    },
    "fannkuchredux": {
      "warmup_itrs": 20,
      "min_bench_itrs": 15,
      "min_bench_time": 0,
      "estimated_time": 0
    },
    "optcarrot": {
      "warmup_itrs": 20,
      "min_bench_itrs": 15,
      "min_bench_time": 0,
      "estimated_time": 0
    },
    "getivar": {
      "warmup_itrs": 20,
      "min_bench_itrs": 802,
      "min_bench_time": 0,
      "estimated_time": 0
    },
    "discourse": {
      "warmup_itrs": 20,
      "min_bench_itrs": 35,
      "min_bench_time": 0,
      "estimated_time": 0
    },
    "chunky_png": {
      "warmup_itrs": 20,
      "min_bench_itrs": 29,
      "min_bench_time": 0,
      "estimated_time": 0
    },
    "nbody": {
      "warmup_itrs": 20,
      "min_bench_itrs": 284,
      "min_bench_time": 0,
      "estimated_time": 0
    },
    "setivar": {
      "warmup_itrs": 20,
      "min_bench_itrs": 1900,
      "min_bench_time": 0,
      "estimated_time": 0
    },
    "erubi": {
      "warmup_itrs": 20,
      "min_bench_itrs": 48,
      "min_bench_time": 0,
      "estimated_time": 0
    }
  },
  "x86_64_prod_ruby_no_jit": {
    "erubi_rails": {
      "warmup_itrs": 5,
      "min_bench_itrs": 971,
      "min_bench_time": 0,
      "itr_time_ms": "27.44",
      "estimated_time": 27
    },
    "fib": {
      "warmup_itrs": 5,
      "min_bench_itrs": 313,
      "min_bench_time": 0,
      "itr_time_ms": "239.31",
      "estimated_time": 77
    },
    "hexapdf": {
      "warmup_itrs": 5,
      "min_bench_itrs": 15,
      "min_bench_time": 0,
      "itr_time_ms": "3222.97",
      "estimated_time": 65
    },
    "rubykon": {
      "warmup_itrs": 5,
      "min_bench_itrs": 15,
      "min_bench_time": 0,
      "itr_time_ms": "12014.96",
      "estimated_time": 241
    },
    "binarytrees": {
      "warmup_itrs": 5,
      "min_bench_itrs": 68,
      "min_bench_time": 0,
      "itr_time_ms": "450.64",
      "estimated_time": 33
    },
    "psych-load": {
      "warmup_itrs": 5,
      "min_bench_itrs": 15,
      "min_bench_time": 0,
      "itr_time_ms": "2532.53",
      "estimated_time": 51
    },
    "30k_ifelse": {
      "warmup_itrs": 5,
      "min_bench_itrs": 55,
      "min_bench_time": 0,
      "itr_time_ms": "2346.52",
      "estimated_time": 141
    },
    "lee": {
      "warmup_itrs": 5,
      "min_bench_itrs": 22,
      "min_bench_time": 0,
      "itr_time_ms": "1218.34",
      "estimated_time": 33
    },
    "mail": {
      "warmup_itrs": 5,
      "min_bench_itrs": 123,
      "min_bench_time": 0,
      "itr_time_ms": "181.10",
      "estimated_time": 24
    },
    "30k_methods": {
      "warmup_itrs": 5,
      "min_bench_itrs": 22,
      "min_bench_time": 0,
      "itr_time_ms": "6539.71",
      "estimated_time": 177
    },
    "cfunc_itself": {
      "warmup_itrs": 5,
      "min_bench_itrs": 446,
      "min_bench_time": 0,
      "itr_time_ms": "107.36",
      "estimated_time": 49
    },
    "railsbench": {
      "warmup_itrs": 5,
      "min_bench_itrs": 15,
      "min_bench_time": 0,
      "itr_time_ms": "2809.66",
      "estimated_time": 57
    },
    "liquid-render": {
      "warmup_itrs": 5,
      "min_bench_itrs": 155,
      "min_bench_time": 0,
      "itr_time_ms": "195.93",
      "estimated_time": 32
    },
    "keyword_args": {
      "warmup_itrs": 5,
      "min_bench_itrs": 379,
      "min_bench_time": 0,
      "itr_time_ms": "285.48",
      "estimated_time": 110
    },
    "respond_to": {
      "warmup_itrs": 5,
      "min_bench_itrs": 101,
      "min_bench_time": 0,
      "itr_time_ms": "276.20",
      "estimated_time": 30
    },
    "activerecord": {
      "warmup_itrs": 5,
      "min_bench_itrs": 182,
      "min_bench_time": 0,
      "itr_time_ms": "152.23",
      "estimated_time": 29
    },
    "fannkuchredux": {
      "warmup_itrs": 5,
      "min_bench_itrs": 15,
      "min_bench_time": 0,
      "itr_time_ms": "7376.20",
      "estimated_time": 148
    },
    "optcarrot": {
      "warmup_itrs": 5,
      "min_bench_itrs": 15,
      "min_bench_time": 0,
      "itr_time_ms": "6209.63",
      "estimated_time": 125
    },
    "getivar": {
      "warmup_itrs": 5,
      "min_bench_itrs": 802,
      "min_bench_time": 0,
      "itr_time_ms": "125.52",
      "estimated_time": 102
    },
    "discourse": {
      "warmup_itrs": 5,
      "min_bench_itrs": 35,
      "min_bench_time": 0,
      "itr_time_ms": "569.63",
      "estimated_time": 23
    },
    "chunky_png": {
      "warmup_itrs": 5,
      "min_bench_itrs": 29,
      "min_bench_time": 0,
      "itr_time_ms": "974.36",
      "estimated_time": 34
    },
    "nbody": {
      "warmup_itrs": 5,
      "min_bench_itrs": 284,
      "min_bench_time": 0,
      "itr_time_ms": "124.67",
      "estimated_time": 37
    },
    "setivar": {
      "warmup_itrs": 5,
      "min_bench_itrs": 1900,
      "min_bench_time": 0,
      "itr_time_ms": "76.87",
      "estimated_time": 147
    },
    "erubi": {
      "warmup_itrs": 5,
      "min_bench_itrs": 48,
      "min_bench_time": 0,
      "itr_time_ms": "454.80",
      "estimated_time": 25
    }
  },
  "x86_64_prod_ruby_with_mjit": {
    "erubi_rails": {
      "warmup_itrs": 75,
      "min_bench_itrs": 971,
      "min_bench_time": 0,
      "itr_time_ms": "29.11",
      "estimated_time": 31
    },
    "fib": {
      "warmup_itrs": 75,
      "min_bench_itrs": 313,
      "min_bench_time": 0,
      "itr_time_ms": "86.44",
      "estimated_time": 34
    },
    "hexapdf": {
      "warmup_itrs": 75,
      "min_bench_itrs": 15,
      "min_bench_time": 0,
      "estimated_time": 0
    },
    "rubykon": {
      "warmup_itrs": 38.727114502220275,
      "min_bench_itrs": 15,
      "min_bench_time": 0,
      "itr_time_ms": "7746.51",
      "estimated_time": 417
    },
    "binarytrees": {
      "warmup_itrs": 75,
      "min_bench_itrs": 68,
      "min_bench_time": 0,
      "itr_time_ms": "292.13",
      "estimated_time": 42
    },
    "psych-load": {
      "warmup_itrs": 75,
      "min_bench_itrs": 15,
      "min_bench_time": 0,
      "itr_time_ms": "2221.46",
      "estimated_time": 200
    },
    "30k_ifelse": {
      "warmup_itrs": 75,
      "min_bench_itrs": 55,
      "min_bench_time": 0,
      "itr_time_ms": "3485.58",
      "estimated_time": 454
    },
    "lee": {
      "warmup_itrs": 75,
      "min_bench_itrs": 22,
      "min_bench_time": 0,
      "itr_time_ms": "1012.12",
      "estimated_time": 99
    },
    "mail": {
      "warmup_itrs": 75,
      "min_bench_itrs": 123,
      "min_bench_time": 0,
      "itr_time_ms": "178.07",
      "estimated_time": 36
    },
    "30k_methods": {
      "warmup_itrs": 29.207938442341245,
      "min_bench_itrs": 22,
      "min_bench_time": 0,
      "itr_time_ms": "10271.18",
      "estimated_time": 526
    },
    "cfunc_itself": {
      "warmup_itrs": 75,
      "min_bench_itrs": 446,
      "min_bench_time": 0,
      "itr_time_ms": "68.59",
      "estimated_time": 36
    },
    "railsbench": {
      "warmup_itrs": 75,
      "min_bench_itrs": 15,
      "min_bench_time": 0,
      "itr_time_ms": "3143.89",
      "estimated_time": 283
    },
    "liquid-render": {
      "warmup_itrs": 75,
      "min_bench_itrs": 155,
      "min_bench_time": 0,
      "itr_time_ms": "184.72",
      "estimated_time": 43
    },
    "keyword_args": {
      "warmup_itrs": 75,
      "min_bench_itrs": 379,
      "min_bench_time": 0,
      "itr_time_ms": "225.84",
      "estimated_time": 103
    },
    "respond_to": {
      "warmup_itrs": 75,
      "min_bench_itrs": 101,
      "min_bench_time": 0,
      "itr_time_ms": "236.63",
      "estimated_time": 42
    },
    "activerecord": {
      "warmup_itrs": 75,
      "min_bench_itrs": 182,
      "min_bench_time": 0,
      "itr_time_ms": "173.35",
      "estimated_time": 45
    },
    "fannkuchredux": {
      "warmup_itrs": 75,
      "min_bench_itrs": 15,
      "min_bench_time": 0,
      "itr_time_ms": "3665.84",
      "estimated_time": 330
    },
    "optcarrot": {
      "warmup_itrs": 75,
      "min_bench_itrs": 15,
      "min_bench_time": 0,
      "itr_time_ms": "2583.18",
      "estimated_time": 233
    },
    "getivar": {
      "warmup_itrs": 75,
      "min_bench_itrs": 802,
      "min_bench_time": 0,
      "itr_time_ms": "24.93",
      "estimated_time": 22
    },
    "discourse": {
      "warmup_itrs": 75,
      "min_bench_itrs": 35,
      "min_bench_time": 0,
      "itr_time_ms": "607.73",
      "estimated_time": 67
    },
    "chunky_png": {
      "warmup_itrs": 75,
      "min_bench_itrs": 29,
      "min_bench_time": 0,
      "itr_time_ms": "798.86",
      "estimated_time": 84
    },
    "nbody": {
      "warmup_itrs": 75,
      "min_bench_itrs": 284,
      "min_bench_time": 0,
      "itr_time_ms": "70.28",
      "estimated_time": 26
    },
    "setivar": {
      "warmup_itrs": 75,
      "min_bench_itrs": 1900,
      "min_bench_time": 0,
      "itr_time_ms": "10.52",
      "estimated_time": 21
    },
    "erubi": {
      "warmup_itrs": 75,
      "min_bench_itrs": 48,
      "min_bench_time": 0,
      "itr_time_ms": "419.37",
      "estimated_time": 52
    }
  },
  "x86_64_prod_ruby_with_yjit": {
    "erubi_rails": {
      "warmup_itrs": 20,
      "min_bench_itrs": 971,
      "min_bench_time": 0,
      "itr_time_ms": "20.59",
      "estimated_time": 21
    },
    "fib": {
      "warmup_itrs": 20,
      "min_bench_itrs": 313,
      "min_bench_time": 0,
      "itr_time_ms": "63.78",
      "estimated_time": 22
    },
    "hexapdf": {
      "warmup_itrs": 20,
      "min_bench_itrs": 15,
      "min_bench_time": 0,
      "itr_time_ms": "2410.22",
      "estimated_time": 85
    },
    "rubykon": {
      "warmup_itrs": 20,
      "min_bench_itrs": 15,
      "min_bench_time": 0,
      "itr_time_ms": "6386.48",
      "estimated_time": 224
    },
    "binarytrees": {
      "warmup_itrs": 20,
      "min_bench_itrs": 68,
      "min_bench_time": 0,
      "itr_time_ms": "342.07",
      "estimated_time": 31
    },
    "psych-load": {
      "warmup_itrs": 20,
      "min_bench_itrs": 15,
      "min_bench_time": 0,
      "itr_time_ms": "1941.93",
      "estimated_time": 68
    },
    "30k_ifelse": {
      "warmup_itrs": 20,
      "min_bench_itrs": 55,
      "min_bench_time": 0,
      "itr_time_ms": "362.80",
      "estimated_time": 28
    },
    "lee": {
      "warmup_itrs": 20,
      "min_bench_itrs": 22,
      "min_bench_time": 0,
      "itr_time_ms": "892.49",
      "estimated_time": 38
    },
    "mail": {
      "warmup_itrs": 20,
      "min_bench_itrs": 123,
      "min_bench_time": 0,
      "itr_time_ms": "161.85",
      "estimated_time": 24
    },
    "30k_methods": {
      "warmup_itrs": 20,
      "min_bench_itrs": 22,
      "min_bench_time": 0,
      "itr_time_ms": "882.86",
      "estimated_time": 38
    },
    "cfunc_itself": {
      "warmup_itrs": 20,
      "min_bench_itrs": 446,
      "min_bench_time": 0,
      "itr_time_ms": "44.82",
      "estimated_time": 21
    },
    "railsbench": {
      "warmup_itrs": 20,
      "min_bench_itrs": 15,
      "min_bench_time": 0,
      "itr_time_ms": "2199.86",
      "estimated_time": 77
    },
    "liquid-render": {
      "warmup_itrs": 20,
      "min_bench_itrs": 155,
      "min_bench_time": 0,
      "itr_time_ms": "128.27",
      "estimated_time": 23
    },
    "keyword_args": {
      "warmup_itrs": 20,
      "min_bench_itrs": 379,
      "min_bench_time": 0,
      "itr_time_ms": "52.73",
      "estimated_time": 22
    },
    "respond_to": {
      "warmup_itrs": 20,
      "min_bench_itrs": 101,
      "min_bench_time": 0,
      "itr_time_ms": "197.17",
      "estimated_time": 24
    },
    "activerecord": {
      "warmup_itrs": 20,
      "min_bench_itrs": 182,
      "min_bench_time": 0,
      "itr_time_ms": "109.58",
      "estimated_time": 23
    },
    "fannkuchredux": {
      "warmup_itrs": 20,
      "min_bench_itrs": 15,
      "min_bench_time": 0,
      "itr_time_ms": "7482.21",
      "estimated_time": 262
    },
    "optcarrot": {
      "warmup_itrs": 20,
      "min_bench_itrs": 15,
      "min_bench_time": 0,
      "itr_time_ms": "3579.49",
      "estimated_time": 126
    },
    "getivar": {
      "warmup_itrs": 20,
      "min_bench_itrs": 802,
      "min_bench_time": 0,
      "itr_time_ms": "42.56",
      "estimated_time": 35
    },
    "discourse": {
      "warmup_itrs": 20,
      "min_bench_itrs": 35,
      "min_bench_time": 0,
      "itr_time_ms": "616.29",
      "estimated_time": 34
    },
    "chunky_png": {
      "warmup_itrs": 20,
      "min_bench_itrs": 29,
      "min_bench_time": 0,
      "itr_time_ms": "669.25",
      "estimated_time": 33
    },
    "nbody": {
      "warmup_itrs": 20,
      "min_bench_itrs": 284,
      "min_bench_time": 0,
      "itr_time_ms": "86.85",
      "estimated_time": 27
    },
    "setivar": {
      "warmup_itrs": 20,
      "min_bench_itrs": 1900,
      "min_bench_time": 0,
      "itr_time_ms": "52.50",
      "estimated_time": 101
    },
    "erubi": {
      "warmup_itrs": 20,
      "min_bench_itrs": 48,
      "min_bench_time": 0,
      "itr_time_ms": "414.08",
      "estimated_time": 29
    }
  },
  "x86_64_yjit_stats": {
    "erubi_rails": {
      "warmup_itrs": 20,
      "min_bench_itrs": 971,
      "min_bench_time": 0,
      "itr_time_ms": "42.30",
      "estimated_time": 42
    },
    "fib": {
      "warmup_itrs": 20,
      "min_bench_itrs": 313,
      "min_bench_time": 0,
      "itr_time_ms": "676.08",
      "estimated_time": 226
    },
    "hexapdf": {
      "warmup_itrs": 20,
      "min_bench_itrs": 15,
      "min_bench_time": 0,
      "itr_time_ms": "7543.65",
      "estimated_time": 265
    },
    "rubykon": {
      "warmup_itrs": 20,
      "min_bench_itrs": 15,
      "min_bench_time": 0,
      "itr_time_ms": "25383.85",
      "estimated_time": 889
    },
    "binarytrees": {
      "warmup_itrs": 20,
      "min_bench_itrs": 68,
      "min_bench_time": 0,
      "itr_time_ms": "1465.96",
      "estimated_time": 130
    },
    "psych-load": {
      "warmup_itrs": 20,
      "min_bench_itrs": 15,
      "min_bench_time": 0,
      "itr_time_ms": "5641.93",
      "estimated_time": 198
    },
    "30k_ifelse": {
      "warmup_itrs": 20,
      "min_bench_itrs": 55,
      "min_bench_time": 0,
      "itr_time_ms": "1347.50",
      "estimated_time": 102
    },
    "lee": {
      "warmup_itrs": 20,
      "min_bench_itrs": 22,
      "min_bench_time": 0,
      "itr_time_ms": "2800.24",
      "estimated_time": 118
    },
    "mail": {
      "warmup_itrs": 20,
      "min_bench_itrs": 123,
      "min_bench_time": 0,
      "itr_time_ms": "413.35",
      "estimated_time": 60
    },
    "30k_methods": {
      "warmup_itrs": 20,
      "min_bench_itrs": 22,
      "min_bench_time": 0,
      "itr_time_ms": "2137.69",
      "estimated_time": 90
    },
    "cfunc_itself": {
      "warmup_itrs": 20,
      "min_bench_itrs": 446,
      "min_bench_time": 0,
      "itr_time_ms": "177.49",
      "estimated_time": 83
    },
    "railsbench": {
      "warmup_itrs": 20,
      "min_bench_itrs": 15,
      "min_bench_time": 0,
      "itr_time_ms": "4082.66",
      "estimated_time": 143
    },
    "liquid-render": {
      "warmup_itrs": 20,
      "min_bench_itrs": 155,
      "min_bench_time": 0,
      "itr_time_ms": "369.74",
      "estimated_time": 65
    },
    "keyword_args": {
      "warmup_itrs": 20,
      "min_bench_itrs": 379,
      "min_bench_time": 0,
      "itr_time_ms": "408.84",
      "estimated_time": 164
    },
    "respond_to": {
      "warmup_itrs": 20,
      "min_bench_itrs": 101,
      "min_bench_time": 0,
      "itr_time_ms": "415.37",
      "estimated_time": 51
    },
    "activerecord": {
      "warmup_itrs": 20,
      "min_bench_itrs": 182,
      "min_bench_time": 0,
      "itr_time_ms": "238.96",
      "estimated_time": 49
    },
    "fannkuchredux": {
      "warmup_itrs": 20,
      "min_bench_itrs": 15,
      "min_bench_time": 0,
      "itr_time_ms": "40869.04",
      "estimated_time": 1431
    },
    "optcarrot": {
      "warmup_itrs": 20,
      "min_bench_itrs": 15,
      "min_bench_time": 0,
      "itr_time_ms": "19280.34",
      "estimated_time": 675
    },
    "getivar": {
      "warmup_itrs": 20,
      "min_bench_itrs": 802,
      "min_bench_time": 0,
      "itr_time_ms": "467.81",
      "estimated_time": 385
    },
    "discourse": {
      "warmup_itrs": 20,
      "min_bench_itrs": 35,
      "min_bench_time": 0,
      "itr_time_ms": "1284.08",
      "estimated_time": 71
    },
    "chunky_png": {
      "warmup_itrs": 20,
      "min_bench_itrs": 29,
      "min_bench_time": 0,
      "itr_time_ms": "3017.41",
      "estimated_time": 148
    },
    "nbody": {
      "warmup_itrs": 20,
      "min_bench_itrs": 284,
      "min_bench_time": 0,
      "itr_time_ms": "311.58",
      "estimated_time": 95
    },
    "setivar": {
      "warmup_itrs": 20,
      "min_bench_itrs": 1900,
      "min_bench_time": 0,
      "itr_time_ms": "316.79",
      "estimated_time": 609
    },
    "erubi": {
      "warmup_itrs": 20,
      "min_bench_itrs": 48,
      "min_bench_time": 0,
      "itr_time_ms": "1160.65",
      "estimated_time": 79
    }
  },
  "estimated_time": 12627
}
