{
  "aarch64_prod_ruby_no_jit": {
    "getivar": {
      "warmup_itrs": 30,
      "min_bench_itrs": 436,
      "min_bench_time": 0,
      "itr_time_ms": "237.55",
      "estimated_time": 111
    },
    "etanni": {
      "warmup_itrs": 30,
      "min_bench_itrs": 48,
      "min_bench_time": 0,
      "itr_time_ms": "909.72",
      "estimated_time": 71
    },
    "ruby-lsp": {
      "warmup_itrs": 30,
      "min_bench_itrs": 344,
      "min_bench_time": 0,
      "itr_time_ms": "212.75",
      "estimated_time": 80
    },
    "railsbench": {
      "warmup_itrs": 30,
      "min_bench_itrs": 15,
      "min_bench_time": 0,
      "itr_time_ms": "7345.85",
      "estimated_time": 331
    },
    "erubi_rails": {
      "warmup_itrs": 30,
      "min_bench_itrs": 1318,
      "min_bench_time": 0,
      "itr_time_ms": "62.65",
      "estimated_time": 85
    },
    "setivar": {
      "warmup_itrs": 30,
      "min_bench_itrs": 1351,
      "min_bench_time": 0,
      "itr_time_ms": "182.90",
      "estimated_time": 253
    },
    "chunky_png": {
      "warmup_itrs": 30,
      "min_bench_itrs": 32,
      "min_bench_time": 0,
      "itr_time_ms": "2268.65",
      "estimated_time": 141
    },
    "activerecord": {
      "warmup_itrs": 30,
      "min_bench_itrs": 473,
      "min_bench_time": 0,
      "itr_time_ms": "197.47",
      "estimated_time": 100
    },
    "hexapdf": {
      "warmup_itrs": 30,
      "min_bench_itrs": 15,
      "min_bench_time": 0,
      "itr_time_ms": "7926.43",
      "estimated_time": 357
    },
    "optcarrot": {
      "warmup_itrs": 30,
      "min_bench_itrs": 15,
      "min_bench_time": 0,
      "itr_time_ms": "16310.05",
      "estimated_time": 734
    },
    "psych-load": {
      "warmup_itrs": 30,
      "min_bench_itrs": 15,
      "min_bench_time": 0,
      "itr_time_ms": "7273.46",
      "estimated_time": 328
    },
    "sequel": {
      "warmup_itrs": 30,
      "min_bench_itrs": 298,
      "min_bench_time": 0,
      "itr_time_ms": "225.80",
      "estimated_time": 75
    },
    "30k_ifelse": {
      "warmup_itrs": 30,
      "min_bench_itrs": 47,
      "min_bench_time": 0,
      "itr_time_ms": "6768.05",
      "estimated_time": 522
    },
    "liquid-c": {
      "warmup_itrs": 30,
      "min_bench_itrs": 338,
      "min_bench_time": 0,
      "itr_time_ms": "227.62",
      "estimated_time": 84
    },
    "30k_methods": {
      "warmup_itrs": 30,
      "min_bench_itrs": 21,
      "min_bench_time": 0,
      "itr_time_ms": "18174.36",
      "estimated_time": 927
    },
    "setivar_young": {
      "warmup_itrs": 30,
      "min_bench_itrs": 432,
      "min_bench_time": 0,
      "itr_time_ms": "289.13",
      "estimated_time": 134
    },
    "ruby-json": {
      "warmup_itrs": 30,
      "min_bench_itrs": 15,
      "min_bench_time": 0,
      "itr_time_ms": "10530.69",
      "estimated_time": 474
    },
    "respond_to": {
      "warmup_itrs": 30,
      "min_bench_itrs": 608,
      "min_bench_time": 0,
      "itr_time_ms": "712.05",
      "estimated_time": 455
    },
    "erubi": {
      "warmup_itrs": 30,
      "min_bench_itrs": 78,
      "min_bench_time": 0,
      "itr_time_ms": "636.62",
      "estimated_time": 69
    },
    "fib": {
      "warmup_itrs": 30,
      "min_bench_itrs": 320,
      "min_bench_time": 0,
      "itr_time_ms": "556.33",
      "estimated_time": 195
    },
    "setivar_object": {
      "warmup_itrs": 30,
      "min_bench_itrs": 417,
      "min_bench_time": 0,
      "itr_time_ms": "290.25",
      "estimated_time": 130
    },
    "cfunc_itself": {
      "warmup_itrs": 30,
      "min_bench_itrs": 491,
      "min_bench_time": 0,
      "itr_time_ms": "271.15",
      "estimated_time": 142
    },
    "throw": {
      "warmup_itrs": 30,
      "min_bench_itrs": 844,
      "min_bench_time": 0,
      "itr_time_ms": "64.36",
      "estimated_time": 57
    },
    "liquid-render": {
      "warmup_itrs": 30,
      "min_bench_itrs": 190,
      "min_bench_time": 0,
      "itr_time_ms": "546.50",
      "estimated_time": 121
    },
    "str_concat": {
      "warmup_itrs": 30,
      "min_bench_itrs": 449,
      "min_bench_time": 0,
      "itr_time_ms": "165.82",
      "estimated_time": 80
    },
    "keyword_args": {
      "warmup_itrs": 30,
      "min_bench_itrs": 373,
      "min_bench_time": 0,
      "itr_time_ms": "717.95",
      "estimated_time": 290
    },
    "fannkuchredux": {
      "warmup_itrs": 30,
      "min_bench_itrs": 23,
      "min_bench_time": 0,
      "itr_time_ms": "5861.64",
      "estimated_time": 311
    },
    "mail": {
      "warmup_itrs": 30,
      "min_bench_itrs": 152,
      "min_bench_time": 0,
      "itr_time_ms": "453.32",
      "estimated_time": 83
    },
    "lee": {
      "warmup_itrs": 30,
      "min_bench_itrs": 21,
      "min_bench_time": 0,
      "itr_time_ms": "3135.26",
      "estimated_time": 160
    },
    "nbody": {
      "warmup_itrs": 30,
      "min_bench_itrs": 273,
      "min_bench_time": 0,
      "itr_time_ms": "285.70",
      "estimated_time": 87
    },
    "rubykon": {
      "warmup_itrs": 30,
      "min_bench_itrs": 15,
      "min_bench_time": 0,
      "itr_time_ms": "32201.06",
      "estimated_time": 1450
    },
    "binarytrees": {
      "warmup_itrs": 30,
      "min_bench_itrs": 85,
      "min_bench_time": 0,
      "itr_time_ms": "990.66",
      "estimated_time": 114
    }
  },
  "aarch64_prod_ruby_with_yjit": {
    "getivar": {
      "warmup_itrs": 30,
      "min_bench_itrs": 436,
      "min_bench_time": 0,
      "itr_time_ms": "107.47",
      "estimated_time": 51
    },
    "etanni": {
      "warmup_itrs": 30,
      "min_bench_itrs": 48,
      "min_bench_time": 0,
      "itr_time_ms": "948.48",
      "estimated_time": 74
    },
    "ruby-lsp": {
      "warmup_itrs": 30,
      "min_bench_itrs": 344,
      "min_bench_time": 0,
      "itr_time_ms": "201.63",
      "estimated_time": 76
    },
    "railsbench": {
      "warmup_itrs": 30,
      "min_bench_itrs": 15,
      "min_bench_time": 0,
      "itr_time_ms": "5452.77",
      "estimated_time": 246
    },
    "erubi_rails": {
      "warmup_itrs": 30,
      "min_bench_itrs": 1318,
      "min_bench_time": 0,
      "itr_time_ms": "44.87",
      "estimated_time": 61
    },
    "setivar": {
      "warmup_itrs": 30,
      "min_bench_itrs": 1351,
      "min_bench_time": 0,
      "itr_time_ms": "50.04",
      "estimated_time": 70
    },
    "chunky_png": {
      "warmup_itrs": 30,
      "min_bench_itrs": 32,
      "min_bench_time": 0,
      "itr_time_ms": "1530.77",
      "estimated_time": 95
    },
    "activerecord": {
      "warmup_itrs": 30,
      "min_bench_itrs": 473,
      "min_bench_time": 0,
      "itr_time_ms": "148.94",
      "estimated_time": 75
    },
    "hexapdf": {
      "warmup_itrs": 30,
      "min_bench_itrs": 15,
      "min_bench_time": 0,
      "itr_time_ms": "6170.68",
      "estimated_time": 278
    },
    "optcarrot": {
      "warmup_itrs": 30,
      "min_bench_itrs": 15,
      "min_bench_time": 0,
      "itr_time_ms": "9497.94",
      "estimated_time": 428
    },
    "psych-load": {
      "warmup_itrs": 30,
      "min_bench_itrs": 15,
      "min_bench_time": 0,
      "itr_time_ms": "5177.33",
      "estimated_time": 233
    },
    "sequel": {
      "warmup_itrs": 30,
      "min_bench_itrs": 298,
      "min_bench_time": 0,
      "itr_time_ms": "201.74",
      "estimated_time": 67
    },
    "30k_ifelse": {
      "warmup_itrs": 30,
      "min_bench_itrs": 47,
      "min_bench_time": 0,
      "itr_time_ms": "1941.72",
      "estimated_time": 150
    },
    "liquid-c": {
      "warmup_itrs": 30,
      "min_bench_itrs": 338,
      "min_bench_time": 0,
      "itr_time_ms": "189.53",
      "estimated_time": 70
    },
    "30k_methods": {
      "warmup_itrs": 30,
      "min_bench_itrs": 21,
      "min_bench_time": 0,
      "itr_time_ms": "3872.87",
      "estimated_time": 198
    },
    "setivar_young": {
      "warmup_itrs": 30,
      "min_bench_itrs": 432,
      "min_bench_time": 0,
      "itr_time_ms": "124.01",
      "estimated_time": 58
    },
    "ruby-json": {
      "warmup_itrs": 30,
      "min_bench_itrs": 15,
      "min_bench_time": 0,
      "itr_time_ms": "8969.87",
      "estimated_time": 404
    },
    "respond_to": {
      "warmup_itrs": 30,
      "min_bench_itrs": 608,
      "min_bench_time": 0,
      "itr_time_ms": "99.06",
      "estimated_time": 64
    },
    "erubi": {
      "warmup_itrs": 30,
      "min_bench_itrs": 78,
      "min_bench_time": 0,
      "itr_time_ms": "561.73",
      "estimated_time": 61
    },
    "fib": {
      "warmup_itrs": 30,
      "min_bench_itrs": 320,
      "min_bench_time": 0,
      "itr_time_ms": "191.09",
      "estimated_time": 67
    },
    "setivar_object": {
      "warmup_itrs": 30,
      "min_bench_itrs": 417,
      "min_bench_time": 0,
      "itr_time_ms": "126.94",
      "estimated_time": 57
    },
    "cfunc_itself": {
      "warmup_itrs": 30,
      "min_bench_itrs": 491,
      "min_bench_time": 0,
      "itr_time_ms": "101.41",
      "estimated_time": 53
    },
    "throw": {
      "warmup_itrs": 30,
      "min_bench_itrs": 844,
      "min_bench_time": 0,
      "itr_time_ms": "50.25",
      "estimated_time": 44
    },
    "liquid-render": {
      "warmup_itrs": 30,
      "min_bench_itrs": 190,
      "min_bench_time": 0,
      "itr_time_ms": "356.36",
      "estimated_time": 79
    },
    "str_concat": {
      "warmup_itrs": 30,
      "min_bench_itrs": 449,
      "min_bench_time": 0,
      "itr_time_ms": "116.19",
      "estimated_time": 56
    },
    "keyword_args": {
      "warmup_itrs": 30,
      "min_bench_itrs": 373,
      "min_bench_time": 0,
      "itr_time_ms": "195.27",
      "estimated_time": 79
    },
    "fannkuchredux": {
      "warmup_itrs": 30,
      "min_bench_itrs": 23,
      "min_bench_time": 0,
      "itr_time_ms": "2029.23",
      "estimated_time": 108
    },
    "mail": {
      "warmup_itrs": 30,
      "min_bench_itrs": 152,
      "min_bench_time": 0,
      "itr_time_ms": "383.54",
      "estimated_time": 70
    },
    "lee": {
      "warmup_itrs": 30,
      "min_bench_itrs": 21,
      "min_bench_time": 0,
      "itr_time_ms": "2323.70",
      "estimated_time": 119
    },
    "nbody": {
      "warmup_itrs": 30,
      "min_bench_itrs": 273,
      "min_bench_time": 0,
      "itr_time_ms": "177.71",
      "estimated_time": 54
    },
    "rubykon": {
      "warmup_itrs": 30,
      "min_bench_itrs": 15,
      "min_bench_time": 0,
      "itr_time_ms": "20723.53",
      "estimated_time": 933
    },
    "binarytrees": {
      "warmup_itrs": 30,
      "min_bench_itrs": 85,
      "min_bench_time": 0,
      "itr_time_ms": "531.82",
      "estimated_time": 62
    }
  },
  "aarch64_yjit_stats": {
    "getivar": {
      "warmup_itrs": 30,
      "min_bench_itrs": 436,
      "min_bench_time": 0,
      "itr_time_ms": "1061.19",
      "estimated_time": 495
    },
    "etanni": {
      "warmup_itrs": 30,
      "min_bench_itrs": 48,
      "min_bench_time": 0,
      "itr_time_ms": "1043.27",
      "estimated_time": 82
    },
    "ruby-lsp": {
      "warmup_itrs": 30,
      "min_bench_itrs": 344,
      "min_bench_time": 0,
      "itr_time_ms": "297.88",
      "estimated_time": 112
    },
    "railsbench": {
      "warmup_itrs": 30,
      "min_bench_itrs": 15,
      "min_bench_time": 0,
      "itr_time_ms": "6895.09",
      "estimated_time": 311
    },
    "erubi_rails": {
      "warmup_itrs": 30,
      "min_bench_itrs": 1318,
      "min_bench_time": 0,
      "itr_time_ms": "61.31",
      "estimated_time": 83
    },
    "setivar": {
      "warmup_itrs": 30,
      "min_bench_itrs": 1351,
      "min_bench_time": 0,
      "itr_time_ms": "595.63",
      "estimated_time": 823
    },
    "chunky_png": {
      "warmup_itrs": 30,
      "min_bench_itrs": 32,
      "min_bench_time": 0,
      "itr_time_ms": "4058.82",
      "estimated_time": 252
    },
    "activerecord": {
      "warmup_itrs": 30,
      "min_bench_itrs": 473,
      "min_bench_time": 0,
      "itr_time_ms": "197.67",
      "estimated_time": 100
    },
    "hexapdf": {
      "warmup_itrs": 30,
      "min_bench_itrs": 15,
      "min_bench_time": 0,
      "itr_time_ms": "10342.73",
      "estimated_time": 466
    },
    "optcarrot": {
      "warmup_itrs": 30,
      "min_bench_itrs": 15,
      "min_bench_time": 0,
      "itr_time_ms": "34246.52",
      "estimated_time": 1542
    },
    "psych-load": {
      "warmup_itrs": 30,
      "min_bench_itrs": 15,
      "min_bench_time": 0,
      "itr_time_ms": "9133.84",
      "estimated_time": 412
    },
    "sequel": {
      "warmup_itrs": 30,
      "min_bench_itrs": 298,
      "min_bench_time": 0,
      "itr_time_ms": "233.12",
      "estimated_time": 77
    },
    "30k_ifelse": {
      "warmup_itrs": 30,
      "min_bench_itrs": 47,
      "min_bench_time": 0,
      "itr_time_ms": "4514.92",
      "estimated_time": 348
    },
    "liquid-c": {
      "warmup_itrs": 30,
      "min_bench_itrs": 338,
      "min_bench_time": 0,
      "itr_time_ms": "222.02",
      "estimated_time": 82
    },
    "30k_methods": {
      "warmup_itrs": 30,
      "min_bench_itrs": 21,
      "min_bench_time": 0,
      "itr_time_ms": "7477.62",
      "estimated_time": 382
    },
    "setivar_young": {
      "warmup_itrs": 30,
      "min_bench_itrs": 432,
      "min_bench_time": 0,
      "itr_time_ms": "653.07",
      "estimated_time": 302
    },
    "ruby-json": {
      "warmup_itrs": 30,
      "min_bench_itrs": 15,
      "min_bench_time": 0,
      "itr_time_ms": "9490.21",
      "estimated_time": 428
    },
    "respond_to": {
      "warmup_itrs": 30,
      "min_bench_itrs": 608,
      "min_bench_time": 0,
      "itr_time_ms": "624.45",
      "estimated_time": 399
    },
    "erubi": {
      "warmup_itrs": 30,
      "min_bench_itrs": 78,
      "min_bench_time": 0,
      "itr_time_ms": "951.06",
      "estimated_time": 103
    },
    "fib": {
      "warmup_itrs": 30,
      "min_bench_itrs": 320,
      "min_bench_time": 0,
      "itr_time_ms": "1601.48",
      "estimated_time": 561
    },
    "setivar_object": {
      "warmup_itrs": 30,
      "min_bench_itrs": 417,
      "min_bench_time": 0,
      "itr_time_ms": "662.98",
      "estimated_time": 297
    },
    "cfunc_itself": {
      "warmup_itrs": 30,
      "min_bench_itrs": 491,
      "min_bench_time": 0,
      "itr_time_ms": "439.33",
      "estimated_time": 229
    },
    "throw": {
      "warmup_itrs": 30,
      "min_bench_itrs": 844,
      "min_bench_time": 0,
      "itr_time_ms": "73.66",
      "estimated_time": 65
    },
    "liquid-render": {
      "warmup_itrs": 30,
      "min_bench_itrs": 190,
      "min_bench_time": 0,
      "itr_time_ms": "575.26",
      "estimated_time": 127
    },
    "str_concat": {
      "warmup_itrs": 30,
      "min_bench_itrs": 449,
      "min_bench_time": 0,
      "itr_time_ms": "600.48",
      "estimated_time": 288
    },
    "keyword_args": {
      "warmup_itrs": 30,
      "min_bench_itrs": 373,
      "min_bench_time": 0,
      "itr_time_ms": "991.38",
      "estimated_time": 400
    },
    "fannkuchredux": {
      "warmup_itrs": 30,
      "min_bench_itrs": 23,
      "min_bench_time": 0,
      "itr_time_ms": "15917.96",
      "estimated_time": 844
    },
    "mail": {
      "warmup_itrs": 30,
      "min_bench_itrs": 152,
      "min_bench_time": 0,
      "itr_time_ms": "595.01",
      "estimated_time": 109
    },
    "lee": {
      "warmup_itrs": 30,
      "min_bench_itrs": 21,
      "min_bench_time": 0,
      "itr_time_ms": "4404.25",
      "estimated_time": 225
    },
    "nbody": {
      "warmup_itrs": 30,
      "min_bench_itrs": 273,
      "min_bench_time": 0,
      "itr_time_ms": "767.09",
      "estimated_time": 233
    },
    "rubykon": {
      "warmup_itrs": 30,
      "min_bench_itrs": 15,
      "min_bench_time": 0,
      "itr_time_ms": "47030.23",
      "estimated_time": 2117
    },
    "binarytrees": {
      "warmup_itrs": 30,
      "min_bench_itrs": 85,
      "min_bench_time": 0,
      "itr_time_ms": "1793.63",
      "estimated_time": 207
    }
  },
  "x86_64_prod_ruby_no_jit": {
    "getivar": {
      "warmup_itrs": 30,
      "min_bench_itrs": 436,
      "min_bench_time": 0,
      "itr_time_ms": "101.80",
      "estimated_time": 48
    },
    "etanni": {
      "warmup_itrs": 30,
      "min_bench_itrs": 48,
      "min_bench_time": 0,
      "itr_time_ms": "416.02",
      "estimated_time": 33
    },
    "ruby-lsp": {
      "warmup_itrs": 30,
      "min_bench_itrs": 344,
      "min_bench_time": 0,
      "itr_time_ms": "79.92",
      "estimated_time": 30
    },
    "railsbench": {
      "warmup_itrs": 30,
      "min_bench_itrs": 15,
      "min_bench_time": 0,
      "itr_time_ms": "2719.44",
      "estimated_time": 123
    },
    "erubi_rails": {
      "warmup_itrs": 30,
      "min_bench_itrs": 1318,
      "min_bench_time": 0,
      "itr_time_ms": "25.75",
      "estimated_time": 35
    },
    "setivar": {
      "warmup_itrs": 30,
      "min_bench_itrs": 1351,
      "min_bench_time": 0,
      "itr_time_ms": "69.96",
      "estimated_time": 97
    },
    "chunky_png": {
      "warmup_itrs": 30,
      "min_bench_itrs": 32,
      "min_bench_time": 0,
      "itr_time_ms": "945.84",
      "estimated_time": 59
    },
    "activerecord": {
      "warmup_itrs": 30,
      "min_bench_itrs": 473,
      "min_bench_time": 0,
      "itr_time_ms": "77.89",
      "estimated_time": 40
    },
    "hexapdf": {
      "warmup_itrs": 30,
      "min_bench_itrs": 15,
      "min_bench_time": 0,
      "itr_time_ms": "3141.39",
      "estimated_time": 142
    },
    "optcarrot": {
      "warmup_itrs": 30,
      "min_bench_itrs": 15,
      "min_bench_time": 0,
      "itr_time_ms": "5898.03",
      "estimated_time": 266
    },
    "psych-load": {
      "warmup_itrs": 30,
      "min_bench_itrs": 15,
      "min_bench_time": 0,
      "itr_time_ms": "2430.61",
      "estimated_time": 110
    },
    "sequel": {
      "warmup_itrs": 30,
      "min_bench_itrs": 298,
      "min_bench_time": 0,
      "itr_time_ms": "86.73",
      "estimated_time": 29
    },
    "30k_ifelse": {
      "warmup_itrs": 30,
      "min_bench_itrs": 47,
      "min_bench_time": 0,
      "itr_time_ms": "2336.04",
      "estimated_time": 180
    },
    "liquid-c": {
      "warmup_itrs": 30,
      "min_bench_itrs": 338,
      "min_bench_time": 0,
      "itr_time_ms": "80.67",
      "estimated_time": 30
    },
    "30k_methods": {
      "warmup_itrs": 30,
      "min_bench_itrs": 21,
      "min_bench_time": 0,
      "itr_time_ms": "7080.56",
      "estimated_time": 362
    },
    "setivar_young": {
      "warmup_itrs": 30,
      "min_bench_itrs": 432,
      "min_bench_time": 0,
      "itr_time_ms": "102.89",
      "estimated_time": 48
    },
    "ruby-json": {
      "warmup_itrs": 30,
      "min_bench_itrs": 15,
      "min_bench_time": 0,
      "itr_time_ms": "3636.36",
      "estimated_time": 164
    },
    "respond_to": {
      "warmup_itrs": 30,
      "min_bench_itrs": 608,
      "min_bench_time": 0,
      "itr_time_ms": "282.37",
      "estimated_time": 181
    },
    "erubi": {
      "warmup_itrs": 30,
      "min_bench_itrs": 78,
      "min_bench_time": 0,
      "itr_time_ms": "301.98",
      "estimated_time": 33
    },
    "fib": {
      "warmup_itrs": 30,
      "min_bench_itrs": 320,
      "min_bench_time": 0,
      "itr_time_ms": "237.16",
      "estimated_time": 84
    },
    "setivar_object": {
      "warmup_itrs": 30,
      "min_bench_itrs": 417,
      "min_bench_time": 0,
      "itr_time_ms": "107.52",
      "estimated_time": 49
    },
    "cfunc_itself": {
      "warmup_itrs": 30,
      "min_bench_itrs": 491,
      "min_bench_time": 0,
      "itr_time_ms": "104.90",
      "estimated_time": 55
    },
    "throw": {
      "warmup_itrs": 30,
      "min_bench_itrs": 844,
      "min_bench_time": 0,
      "itr_time_ms": "29.48",
      "estimated_time": 26
    },
    "liquid-render": {
      "warmup_itrs": 30,
      "min_bench_itrs": 190,
      "min_bench_time": 0,
      "itr_time_ms": "194.91",
      "estimated_time": 43
    },
    "str_concat": {
      "warmup_itrs": 30,
      "min_bench_itrs": 449,
      "min_bench_time": 0,
      "itr_time_ms": "79.97",
      "estimated_time": 39
    },
    "keyword_args": {
      "warmup_itrs": 30,
      "min_bench_itrs": 373,
      "min_bench_time": 0,
      "itr_time_ms": "288.33",
      "estimated_time": 117
    },
    "fannkuchredux": {
      "warmup_itrs": 30,
      "min_bench_itrs": 23,
      "min_bench_time": 0,
      "itr_time_ms": "2112.16",
      "estimated_time": 112
    },
    "mail": {
      "warmup_itrs": 30,
      "min_bench_itrs": 152,
      "min_bench_time": 0,
      "itr_time_ms": "166.99",
      "estimated_time": 31
    },
    "lee": {
      "warmup_itrs": 30,
      "min_bench_itrs": 21,
      "min_bench_time": 0,
      "itr_time_ms": "1252.31",
      "estimated_time": 64
    },
    "nbody": {
      "warmup_itrs": 30,
      "min_bench_itrs": 273,
      "min_bench_time": 0,
      "itr_time_ms": "133.99",
      "estimated_time": 41
    },
    "rubykon": {
      "warmup_itrs": 30,
      "min_bench_itrs": 15,
      "min_bench_time": 0,
      "itr_time_ms": "12177.46",
      "estimated_time": 548
    },
    "binarytrees": {
      "warmup_itrs": 30,
      "min_bench_itrs": 85,
      "min_bench_time": 0,
      "itr_time_ms": "457.22",
      "estimated_time": 53
    }
  },
  "x86_64_prod_ruby_with_yjit": {
    "getivar": {
      "warmup_itrs": 30,
      "min_bench_itrs": 436,
      "min_bench_time": 0,
      "itr_time_ms": "45.79",
      "estimated_time": 22
    },
    "etanni": {
      "warmup_itrs": 30,
      "min_bench_itrs": 48,
      "min_bench_time": 0,
      "itr_time_ms": "415.99",
      "estimated_time": 33
    },
    "ruby-lsp": {
      "warmup_itrs": 30,
      "min_bench_itrs": 344,
      "min_bench_time": 0,
      "itr_time_ms": "58.14",
      "estimated_time": 22
    },
    "railsbench": {
      "warmup_itrs": 30,
      "min_bench_itrs": 15,
      "min_bench_time": 0,
      "itr_time_ms": "1813.26",
      "estimated_time": 82
    },
    "erubi_rails": {
      "warmup_itrs": 30,
      "min_bench_itrs": 1318,
      "min_bench_time": 0,
      "itr_time_ms": "15.17",
      "estimated_time": 21
    },
    "setivar": {
      "warmup_itrs": 30,
      "min_bench_itrs": 1351,
      "min_bench_time": 0,
      "itr_time_ms": "14.79",
      "estimated_time": 21
    },
    "chunky_png": {
      "warmup_itrs": 30,
      "min_bench_itrs": 32,
      "min_bench_time": 0,
      "itr_time_ms": "617.95",
      "estimated_time": 39
    },
    "activerecord": {
      "warmup_itrs": 30,
      "min_bench_itrs": 473,
      "min_bench_time": 0,
      "itr_time_ms": "42.25",
      "estimated_time": 22
    },
    "hexapdf": {
      "warmup_itrs": 30,
      "min_bench_itrs": 15,
      "min_bench_time": 0,
      "itr_time_ms": "2017.65",
      "estimated_time": 91
    },
    "optcarrot": {
      "warmup_itrs": 30,
      "min_bench_itrs": 15,
      "min_bench_time": 0,
      "itr_time_ms": "2570.05",
      "estimated_time": 116
    },
    "psych-load": {
      "warmup_itrs": 30,
      "min_bench_itrs": 15,
      "min_bench_time": 0,
      "itr_time_ms": "1850.62",
      "estimated_time": 84
    },
    "sequel": {
      "warmup_itrs": 30,
      "min_bench_itrs": 298,
      "min_bench_time": 0,
      "itr_time_ms": "66.99",
      "estimated_time": 22
    },
    "30k_ifelse": {
      "warmup_itrs": 30,
      "min_bench_itrs": 47,
      "min_bench_time": 0,
      "itr_time_ms": "422.53",
      "estimated_time": 33
    },
    "liquid-c": {
      "warmup_itrs": 30,
      "min_bench_itrs": 338,
      "min_bench_time": 0,
      "itr_time_ms": "59.15",
      "estimated_time": 22
    },
    "30k_methods": {
      "warmup_itrs": 30,
      "min_bench_itrs": 21,
      "min_bench_time": 0,
      "itr_time_ms": "950.85",
      "estimated_time": 49
    },
    "setivar_young": {
      "warmup_itrs": 30,
      "min_bench_itrs": 432,
      "min_bench_time": 0,
      "itr_time_ms": "46.24",
      "estimated_time": 22
    },
    "ruby-json": {
      "warmup_itrs": 30,
      "min_bench_itrs": 15,
      "min_bench_time": 0,
      "itr_time_ms": "3073.71",
      "estimated_time": 139
    },
    "respond_to": {
      "warmup_itrs": 30,
      "min_bench_itrs": 608,
      "min_bench_time": 0,
      "itr_time_ms": "32.89",
      "estimated_time": 21
    },
    "erubi": {
      "warmup_itrs": 30,
      "min_bench_itrs": 78,
      "min_bench_time": 0,
      "itr_time_ms": "253.17",
      "estimated_time": 28
    },
    "fib": {
      "warmup_itrs": 30,
      "min_bench_itrs": 320,
      "min_bench_time": 0,
      "itr_time_ms": "62.42",
      "estimated_time": 22
    },
    "setivar_object": {
      "warmup_itrs": 30,
      "min_bench_itrs": 417,
      "min_bench_time": 0,
      "itr_time_ms": "47.92",
      "estimated_time": 22
    },
    "cfunc_itself": {
      "warmup_itrs": 30,
      "min_bench_itrs": 491,
      "min_bench_time": 0,
      "itr_time_ms": "40.72",
      "estimated_time": 22
    },
    "throw": {
      "warmup_itrs": 30,
      "min_bench_itrs": 844,
      "min_bench_time": 0,
      "itr_time_ms": "23.69",
      "estimated_time": 21
    },
    "liquid-render": {
      "warmup_itrs": 30,
      "min_bench_itrs": 190,
      "min_bench_time": 0,
      "itr_time_ms": "104.85",
      "estimated_time": 24
    },
    "str_concat": {
      "warmup_itrs": 30,
      "min_bench_itrs": 449,
      "min_bench_time": 0,
      "itr_time_ms": "44.47",
      "estimated_time": 22
    },
    "keyword_args": {
      "warmup_itrs": 30,
      "min_bench_itrs": 373,
      "min_bench_time": 0,
      "itr_time_ms": "53.61",
      "estimated_time": 22
    },
    "fannkuchredux": {
      "warmup_itrs": 30,
      "min_bench_itrs": 23,
      "min_bench_time": 0,
      "itr_time_ms": "869.40",
      "estimated_time": 47
    },
    "mail": {
      "warmup_itrs": 30,
      "min_bench_itrs": 152,
      "min_bench_time": 0,
      "itr_time_ms": "131.36",
      "estimated_time": 24
    },
    "lee": {
      "warmup_itrs": 30,
      "min_bench_itrs": 21,
      "min_bench_time": 0,
      "itr_time_ms": "913.60",
      "estimated_time": 47
    },
    "nbody": {
      "warmup_itrs": 30,
      "min_bench_itrs": 273,
      "min_bench_time": 0,
      "itr_time_ms": "73.12",
      "estimated_time": 23
    },
    "rubykon": {
      "warmup_itrs": 30,
      "min_bench_itrs": 15,
      "min_bench_time": 0,
      "itr_time_ms": "6706.43",
      "estimated_time": 302
    },
    "binarytrees": {
      "warmup_itrs": 30,
      "min_bench_itrs": 85,
      "min_bench_time": 0,
      "itr_time_ms": "234.65",
      "estimated_time": 27
    }
  },
  "x86_64_yjit_stats": {
    "getivar": {
      "warmup_itrs": 30,
      "min_bench_itrs": 436,
      "min_bench_time": 0,
      "itr_time_ms": "457.31",
      "estimated_time": 214
    },
    "etanni": {
      "warmup_itrs": 30,
      "min_bench_itrs": 48,
      "min_bench_time": 0,
      "itr_time_ms": "442.26",
      "estimated_time": 35
    },
    "ruby-lsp": {
      "warmup_itrs": 30,
      "min_bench_itrs": 344,
      "min_bench_time": 0,
      "itr_time_ms": "106.75",
      "estimated_time": 40
    },
    "railsbench": {
      "warmup_itrs": 30,
      "min_bench_itrs": 15,
      "min_bench_time": 0,
      "itr_time_ms": "2185.67",
      "estimated_time": 99
    },
    "erubi_rails": {
      "warmup_itrs": 30,
      "min_bench_itrs": 1318,
      "min_bench_time": 0,
      "itr_time_ms": "21.31",
      "estimated_time": 29
    },
    "setivar": {
      "warmup_itrs": 30,
      "min_bench_itrs": 1351,
      "min_bench_time": 0,
      "itr_time_ms": "230.49",
      "estimated_time": 319
    },
    "chunky_png": {
      "warmup_itrs": 30,
      "min_bench_itrs": 32,
      "min_bench_time": 0,
      "itr_time_ms": "1748.93",
      "estimated_time": 109
    },
    "activerecord": {
      "warmup_itrs": 30,
      "min_bench_itrs": 473,
      "min_bench_time": 0,
      "itr_time_ms": "63.56",
      "estimated_time": 32
    },
    "hexapdf": {
      "warmup_itrs": 30,
      "min_bench_itrs": 15,
      "min_bench_time": 0,
      "itr_time_ms": "3999.63",
      "estimated_time": 180
    },
    "optcarrot": {
      "warmup_itrs": 30,
      "min_bench_itrs": 15,
      "min_bench_time": 0,
      "itr_time_ms": "14723.07",
      "estimated_time": 663
    },
    "psych-load": {
      "warmup_itrs": 30,
      "min_bench_itrs": 15,
      "min_bench_time": 0,
      "itr_time_ms": "3400.51",
      "estimated_time": 154
    },
    "sequel": {
      "warmup_itrs": 30,
      "min_bench_itrs": 298,
      "min_bench_time": 0,
      "itr_time_ms": "78.57",
      "estimated_time": 26
    },
    "30k_ifelse": {
      "warmup_itrs": 30,
      "min_bench_itrs": 47,
      "min_bench_time": 0,
      "itr_time_ms": "1350.87",
      "estimated_time": 105
    },
    "liquid-c": {
      "warmup_itrs": 30,
      "min_bench_itrs": 338,
      "min_bench_time": 0,
      "itr_time_ms": "70.95",
      "estimated_time": 27
    },
    "30k_methods": {
      "warmup_itrs": 30,
      "min_bench_itrs": 21,
      "min_bench_time": 0,
      "itr_time_ms": "2452.66",
      "estimated_time": 126
    },
    "setivar_young": {
      "warmup_itrs": 30,
      "min_bench_itrs": 432,
      "min_bench_time": 0,
      "itr_time_ms": "280.41",
      "estimated_time": 130
    },
    "ruby-json": {
      "warmup_itrs": 30,
      "min_bench_itrs": 15,
      "min_bench_time": 0,
      "itr_time_ms": "3679.85",
      "estimated_time": 166
    },
    "respond_to": {
      "warmup_itrs": 30,
      "min_bench_itrs": 608,
      "min_bench_time": 0,
      "itr_time_ms": "238.47",
      "estimated_time": 153
    },
    "erubi": {
      "warmup_itrs": 30,
      "min_bench_itrs": 78,
      "min_bench_time": 0,
      "itr_time_ms": "373.23",
      "estimated_time": 41
    },
    "fib": {
      "warmup_itrs": 30,
      "min_bench_itrs": 320,
      "min_bench_time": 0,
      "itr_time_ms": "695.66",
      "estimated_time": 244
    },
    "setivar_object": {
      "warmup_itrs": 30,
      "min_bench_itrs": 417,
      "min_bench_time": 0,
      "itr_time_ms": "277.18",
      "estimated_time": 124
    },
    "cfunc_itself": {
      "warmup_itrs": 30,
      "min_bench_itrs": 491,
      "min_bench_time": 0,
      "itr_time_ms": "196.64",
      "estimated_time": 103
    },
    "throw": {
      "warmup_itrs": 30,
      "min_bench_itrs": 844,
      "min_bench_time": 0,
      "itr_time_ms": "33.59",
      "estimated_time": 30
    },
    "liquid-render": {
      "warmup_itrs": 30,
      "min_bench_itrs": 190,
      "min_bench_time": 0,
      "itr_time_ms": "198.14",
      "estimated_time": 44
    },
    "str_concat": {
      "warmup_itrs": 30,
      "min_bench_itrs": 449,
      "min_bench_time": 0,
      "itr_time_ms": "239.62",
      "estimated_time": 115
    },
    "keyword_args": {
      "warmup_itrs": 30,
      "min_bench_itrs": 373,
      "min_bench_time": 0,
      "itr_time_ms": "428.29",
      "estimated_time": 173
    },
    "fannkuchredux": {
      "warmup_itrs": 30,
      "min_bench_itrs": 23,
      "min_bench_time": 0,
      "itr_time_ms": "6530.10",
      "estimated_time": 347
    },
    "mail": {
      "warmup_itrs": 30,
      "min_bench_itrs": 152,
      "min_bench_time": 0,
      "itr_time_ms": "213.09",
      "estimated_time": 39
    },
    "lee": {
      "warmup_itrs": 30,
      "min_bench_itrs": 21,
      "min_bench_time": 0,
      "itr_time_ms": "1697.25",
      "estimated_time": 87
    },
    "nbody": {
      "warmup_itrs": 30,
      "min_bench_itrs": 273,
      "min_bench_time": 0,
      "itr_time_ms": "332.47",
      "estimated_time": 101
    },
    "rubykon": {
      "warmup_itrs": 30,
      "min_bench_itrs": 15,
      "min_bench_time": 0,
      "itr_time_ms": "18445.32",
      "estimated_time": 831
    },
    "binarytrees": {
      "warmup_itrs": 30,
      "min_bench_itrs": 85,
      "min_bench_time": 0,
      "itr_time_ms": "794.87",
      "estimated_time": 92
    }
  },
  "aarch64_estimated_time": 13091,
  "x86_64_estimated_time": 4786
}
