{
  "prod_ruby_no_jit": {
    "fib": {
      "warmup_itrs": 5,
      "min_bench_itrs": 319,
      "min_bench_time": 0,
      "itr_time_ms": 242.66234157916426,
      "estimated_time": 79
    },
    "30k_methods": {
      "warmup_itrs": 5,
      "min_bench_itrs": 22,
      "min_bench_time": 0,
      "itr_time_ms": 6341.820273844694,
      "estimated_time": 172
    },
    "liquid-render": {
      "warmup_itrs": 5,
      "min_bench_itrs": 156,
      "min_bench_time": 0,
      "itr_time_ms": 192.50814855480806,
      "estimated_time": 31
    },
    "activerecord": {
      "warmup_itrs": 5,
      "min_bench_itrs": 184,
      "min_bench_time": 0,
      "itr_time_ms": 153.4966335925476,
      "estimated_time": 30
    },
    "binarytrees": {
      "warmup_itrs": 5,
      "min_bench_itrs": 63,
      "min_bench_time": 0,
      "itr_time_ms": 474.3582172319293,
      "estimated_time": 33
    },
    "discourse": {
      "warmup_itrs": 5,
      "min_bench_itrs": 38,
      "min_bench_time": 0,
      "itr_time_ms": 566.2676167441532,
      "estimated_time": 25
    },
    "rubykon": {
      "warmup_itrs": 5,
      "min_bench_itrs": 15,
      "min_bench_time": 0,
      "itr_time_ms": 13516.20548379918,
      "estimated_time": 271
    },
    "psych-load": {
      "warmup_itrs": 5,
      "min_bench_itrs": 15,
      "min_bench_time": 0,
      "itr_time_ms": 2514.4769615804157,
      "estimated_time": 51
    },
    "hexapdf": {
      "warmup_itrs": 5,
      "min_bench_itrs": 15,
      "min_bench_time": 0,
      "itr_time_ms": 3212.423370654384,
      "estimated_time": 65
    },
    "optcarrot": {
      "warmup_itrs": 5,
      "min_bench_itrs": 15,
      "min_bench_time": 0,
      "itr_time_ms": 6105.331467650831,
      "estimated_time": 123
    },
    "setivar": {
      "warmup_itrs": 5,
      "min_bench_itrs": 1902,
      "min_bench_time": 0,
      "itr_time_ms": 81.51924132194901,
      "estimated_time": 156
    },
    "lee": {
      "warmup_itrs": 5,
      "min_bench_itrs": 21,
      "min_bench_time": 0,
      "itr_time_ms": 1213.1431689062579,
      "estimated_time": 32
    },
    "chunky_png": {
      "warmup_itrs": 5,
      "min_bench_itrs": 30,
      "min_bench_time": 0,
      "itr_time_ms": 988.0317463378968,
      "estimated_time": 35
    },
    "fannkuchredux": {
      "warmup_itrs": 5,
      "min_bench_itrs": 15,
      "min_bench_time": 0,
      "itr_time_ms": 6882.821856687467,
      "estimated_time": 138
    },
    "mail": {
      "warmup_itrs": 5,
      "min_bench_itrs": 123,
      "min_bench_time": 0,
      "itr_time_ms": 184.27765943352284,
      "estimated_time": 24
    },
    "railsbench": {
      "warmup_itrs": 5,
      "min_bench_itrs": 15,
      "min_bench_time": 0,
      "itr_time_ms": 2802.567961998284,
      "estimated_time": 57
    },
    "keyword_args": {
      "warmup_itrs": 5,
      "min_bench_itrs": 373,
      "min_bench_time": 0,
      "itr_time_ms": 288.03263016124356,
      "estimated_time": 109
    },
    "30k_ifelse": {
      "warmup_itrs": 5,
      "min_bench_itrs": 56,
      "min_bench_time": 0,
      "itr_time_ms": 2281.693083945323,
      "estimated_time": 140
    },
    "cfunc_itself": {
      "warmup_itrs": 5,
      "min_bench_itrs": 449,
      "min_bench_time": 0,
      "itr_time_ms": 105.61927591327586,
      "estimated_time": 48
    },
    "respond_to": {
      "warmup_itrs": 5,
      "min_bench_itrs": 108,
      "min_bench_time": 0,
      "itr_time_ms": 274.71873824569315,
      "estimated_time": 32
    },
    "getivar": {
      "warmup_itrs": 5,
      "min_bench_itrs": 786,
      "min_bench_time": 0,
      "itr_time_ms": 110.66538003554645,
      "estimated_time": 88
    },
    "nbody": {
      "warmup_itrs": 5,
      "min_bench_itrs": 275,
      "min_bench_time": 0,
      "itr_time_ms": 120.88128704916348,
      "estimated_time": 34
    },
    "erubi_rails": {
      "warmup_itrs": 5,
      "min_bench_itrs": 982,
      "min_bench_time": 0,
      "itr_time_ms": 26.832424836736624,
      "estimated_time": 27
    },
    "erubi": {
      "warmup_itrs": 5,
      "min_bench_itrs": 47,
      "min_bench_time": 0,
      "itr_time_ms": 459.23920389898916,
      "estimated_time": 24
    }
  },
  "prod_ruby_with_mjit": {
    "fib": {
      "warmup_itrs": 75,
      "min_bench_itrs": 319,
      "min_bench_time": 0,
      "itr_time_ms": 86.22278038669249,
      "estimated_time": 34
    },
    "30k_methods": {
      "warmup_itrs": 29.358817570533084,
      "min_bench_itrs": 22,
      "min_bench_time": 0,
      "itr_time_ms": 10218.395181592892,
      "estimated_time": 525
    },
    "liquid-render": {
      "warmup_itrs": 75,
      "min_bench_itrs": 156,
      "min_bench_time": 0,
      "itr_time_ms": 185.60246959662973,
      "estimated_time": 43
    },
    "activerecord": {
      "warmup_itrs": 75,
      "min_bench_itrs": 184,
      "min_bench_time": 0,
      "itr_time_ms": 174.02556889852428,
      "estimated_time": 46
    },
    "binarytrees": {
      "warmup_itrs": 75,
      "min_bench_itrs": 63,
      "min_bench_time": 0,
      "itr_time_ms": 316.6451609848688,
      "estimated_time": 44
    },
    "discourse": {
      "warmup_itrs": 75,
      "min_bench_itrs": 38,
      "min_bench_time": 0,
      "itr_time_ms": 584.6026808256283,
      "estimated_time": 67
    },
    "rubykon": {
      "warmup_itrs": 27.746313167857576,
      "min_bench_itrs": 15,
      "min_bench_time": 0,
      "itr_time_ms": 10812.247313186526,
      "estimated_time": 463
    },
    "psych-load": {
      "warmup_itrs": 75,
      "min_bench_itrs": 15,
      "min_bench_time": 0,
      "itr_time_ms": 2273.277824061612,
      "estimated_time": 205
    },
    "hexapdf": {
      "warmup_itrs": 75,
      "min_bench_itrs": 15,
      "min_bench_time": 0,
      "estimated_time": 0
    },
    "optcarrot": {
      "warmup_itrs": 75,
      "min_bench_itrs": 15,
      "min_bench_time": 0,
      "itr_time_ms": 2582.837704072396,
      "estimated_time": 233
    },
    "setivar": {
      "warmup_itrs": 75,
      "min_bench_itrs": 1902,
      "min_bench_time": 0,
      "itr_time_ms": 10.513693369155714,
      "estimated_time": 21
    },
    "lee": {
      "warmup_itrs": 75,
      "min_bench_itrs": 21,
      "min_bench_time": 0,
      "itr_time_ms": 1003.6594409241595,
      "estimated_time": 97
    },
    "chunky_png": {
      "warmup_itrs": 75,
      "min_bench_itrs": 30,
      "min_bench_time": 0,
      "itr_time_ms": 795.4031870347159,
      "estimated_time": 84
    },
    "fannkuchredux": {
      "warmup_itrs": 75,
      "min_bench_itrs": 15,
      "min_bench_time": 0,
      "itr_time_ms": 3979.3553495158753,
      "estimated_time": 359
    },
    "mail": {
      "warmup_itrs": 75,
      "min_bench_itrs": 123,
      "min_bench_time": 0,
      "itr_time_ms": 178.04973223435928,
      "estimated_time": 36
    },
    "railsbench": {
      "warmup_itrs": 75,
      "min_bench_itrs": 15,
      "min_bench_time": 0,
      "itr_time_ms": 3154.1211685165763,
      "estimated_time": 284
    },
    "keyword_args": {
      "warmup_itrs": 75,
      "min_bench_itrs": 373,
      "min_bench_time": 0,
      "itr_time_ms": 220.32090261122806,
      "estimated_time": 99
    },
    "30k_ifelse": {
      "warmup_itrs": 75,
      "min_bench_itrs": 56,
      "min_bench_time": 0,
      "itr_time_ms": 3449.820420078256,
      "estimated_time": 452
    },
    "cfunc_itself": {
      "warmup_itrs": 75,
      "min_bench_itrs": 449,
      "min_bench_time": 0,
      "itr_time_ms": 72.23949368243049,
      "estimated_time": 38
    },
    "respond_to": {
      "warmup_itrs": 75,
      "min_bench_itrs": 108,
      "min_bench_time": 0,
      "itr_time_ms": 234.3435895713893,
      "estimated_time": 43
    },
    "getivar": {
      "warmup_itrs": 75,
      "min_bench_itrs": 786,
      "min_bench_time": 0,
      "itr_time_ms": 25.419463023960514,
      "estimated_time": 22
    },
    "nbody": {
      "warmup_itrs": 75,
      "min_bench_itrs": 275,
      "min_bench_time": 0,
      "itr_time_ms": 72.59241138330914,
      "estimated_time": 26
    },
    "erubi_rails": {
      "warmup_itrs": 75,
      "min_bench_itrs": 982,
      "min_bench_time": 0,
      "itr_time_ms": 29.791209122046563,
      "estimated_time": 32
    },
    "erubi": {
      "warmup_itrs": 75,
      "min_bench_itrs": 47,
      "min_bench_time": 0,
      "itr_time_ms": 423.9424858440427,
      "estimated_time": 52
    }
  },
  "prod_ruby_with_yjit": {
    "fib": {
      "warmup_itrs": 20,
      "min_bench_itrs": 319,
      "min_bench_time": 0,
      "itr_time_ms": 62.53675779847423,
      "estimated_time": 22
    },
    "30k_methods": {
      "warmup_itrs": 20,
      "min_bench_itrs": 22,
      "min_bench_time": 0,
      "itr_time_ms": 879.112331662327,
      "estimated_time": 37
    },
    "liquid-render": {
      "warmup_itrs": 20,
      "min_bench_itrs": 156,
      "min_bench_time": 0,
      "itr_time_ms": 127.55561984168031,
      "estimated_time": 23
    },
    "activerecord": {
      "warmup_itrs": 20,
      "min_bench_itrs": 184,
      "min_bench_time": 0,
      "itr_time_ms": 108.48656419219206,
      "estimated_time": 23
    },
    "binarytrees": {
      "warmup_itrs": 20,
      "min_bench_itrs": 63,
      "min_bench_time": 0,
      "itr_time_ms": 368.2448599797984,
      "estimated_time": 31
    },
    "discourse": {
      "warmup_itrs": 20,
      "min_bench_itrs": 38,
      "min_bench_time": 0,
      "itr_time_ms": 513.3444421458989,
      "estimated_time": 30
    },
    "rubykon": {
      "warmup_itrs": 20,
      "min_bench_itrs": 15,
      "min_bench_time": 0,
      "itr_time_ms": 7884.241657828291,
      "estimated_time": 276
    },
    "psych-load": {
      "warmup_itrs": 20,
      "min_bench_itrs": 15,
      "min_bench_time": 0,
      "itr_time_ms": 1972.056071832776,
      "estimated_time": 70
    },
    "hexapdf": {
      "warmup_itrs": 20,
      "min_bench_itrs": 15,
      "min_bench_time": 0,
      "itr_time_ms": 2416.375797304014,
      "estimated_time": 85
    },
    "optcarrot": {
      "warmup_itrs": 20,
      "min_bench_itrs": 15,
      "min_bench_time": 0,
      "itr_time_ms": 3452.2637153044343,
      "estimated_time": 121
    },
    "setivar": {
      "warmup_itrs": 20,
      "min_bench_itrs": 1902,
      "min_bench_time": 0,
      "itr_time_ms": 52.52415741355849,
      "estimated_time": 101
    },
    "lee": {
      "warmup_itrs": 20,
      "min_bench_itrs": 21,
      "min_bench_time": 0,
      "itr_time_ms": 931.58193516799,
      "estimated_time": 39
    },
    "chunky_png": {
      "warmup_itrs": 20,
      "min_bench_itrs": 30,
      "min_bench_time": 0,
      "itr_time_ms": 657.7002366619378,
      "estimated_time": 33
    },
    "fannkuchredux": {
      "warmup_itrs": 20,
      "min_bench_itrs": 15,
      "min_bench_time": 0,
      "itr_time_ms": 6930.194767626624,
      "estimated_time": 243
    },
    "mail": {
      "warmup_itrs": 20,
      "min_bench_itrs": 123,
      "min_bench_time": 0,
      "itr_time_ms": 162.26208732440705,
      "estimated_time": 24
    },
    "railsbench": {
      "warmup_itrs": 20,
      "min_bench_itrs": 15,
      "min_bench_time": 0,
      "itr_time_ms": 2177.3943999782205,
      "estimated_time": 77
    },
    "keyword_args": {
      "warmup_itrs": 20,
      "min_bench_itrs": 373,
      "min_bench_time": 0,
      "itr_time_ms": 53.4990481844053,
      "estimated_time": 22
    },
    "30k_ifelse": {
      "warmup_itrs": 20,
      "min_bench_itrs": 56,
      "min_bench_time": 0,
      "itr_time_ms": 353.9949108931151,
      "estimated_time": 27
    },
    "cfunc_itself": {
      "warmup_itrs": 20,
      "min_bench_itrs": 449,
      "min_bench_time": 0,
      "itr_time_ms": 44.516438176601255,
      "estimated_time": 21
    },
    "respond_to": {
      "warmup_itrs": 20,
      "min_bench_itrs": 108,
      "min_bench_time": 0,
      "itr_time_ms": 183.88089511374181,
      "estimated_time": 24
    },
    "getivar": {
      "warmup_itrs": 20,
      "min_bench_itrs": 786,
      "min_bench_time": 0,
      "itr_time_ms": 42.55552419757199,
      "estimated_time": 35
    },
    "nbody": {
      "warmup_itrs": 20,
      "min_bench_itrs": 275,
      "min_bench_time": 0,
      "itr_time_ms": 90.92336129058491,
      "estimated_time": 27
    },
    "erubi_rails": {
      "warmup_itrs": 20,
      "min_bench_itrs": 982,
      "min_bench_time": 0,
      "itr_time_ms": 20.364151474335216,
      "estimated_time": 21
    },
    "erubi": {
      "warmup_itrs": 20,
      "min_bench_itrs": 47,
      "min_bench_time": 0,
      "itr_time_ms": 420.2330776272302,
      "estimated_time": 29
    }
  },
  "yjit_rust_proto": {
    "fib": {
      "warmup_itrs": 20,
      "min_bench_itrs": 319,
      "min_bench_time": 0,
      "estimated_time": 0
    },
    "30k_methods": {
      "warmup_itrs": 20,
      "min_bench_itrs": 22,
      "min_bench_time": 0,
      "estimated_time": 0
    },
    "liquid-render": {
      "warmup_itrs": 20,
      "min_bench_itrs": 156,
      "min_bench_time": 0,
      "estimated_time": 0
    },
    "activerecord": {
      "warmup_itrs": 20,
      "min_bench_itrs": 184,
      "min_bench_time": 0,
      "estimated_time": 0
    },
    "binarytrees": {
      "warmup_itrs": 20,
      "min_bench_itrs": 63,
      "min_bench_time": 0,
      "estimated_time": 0
    },
    "discourse": {
      "warmup_itrs": 20,
      "min_bench_itrs": 38,
      "min_bench_time": 0,
      "estimated_time": 0
    },
    "rubykon": {
      "warmup_itrs": 20,
      "min_bench_itrs": 15,
      "min_bench_time": 0,
      "estimated_time": 0
    },
    "psych-load": {
      "warmup_itrs": 20,
      "min_bench_itrs": 15,
      "min_bench_time": 0,
      "estimated_time": 0
    },
    "hexapdf": {
      "warmup_itrs": 20,
      "min_bench_itrs": 15,
      "min_bench_time": 0,
      "estimated_time": 0
    },
    "optcarrot": {
      "warmup_itrs": 20,
      "min_bench_itrs": 15,
      "min_bench_time": 0,
      "estimated_time": 0
    },
    "setivar": {
      "warmup_itrs": 20,
      "min_bench_itrs": 1902,
      "min_bench_time": 0,
      "estimated_time": 0
    },
    "lee": {
      "warmup_itrs": 20,
      "min_bench_itrs": 21,
      "min_bench_time": 0,
      "estimated_time": 0
    },
    "chunky_png": {
      "warmup_itrs": 20,
      "min_bench_itrs": 30,
      "min_bench_time": 0,
      "estimated_time": 0
    },
    "fannkuchredux": {
      "warmup_itrs": 20,
      "min_bench_itrs": 15,
      "min_bench_time": 0,
      "estimated_time": 0
    },
    "mail": {
      "warmup_itrs": 20,
      "min_bench_itrs": 123,
      "min_bench_time": 0,
      "estimated_time": 0
    },
    "railsbench": {
      "warmup_itrs": 20,
      "min_bench_itrs": 15,
      "min_bench_time": 0,
      "estimated_time": 0
    },
    "keyword_args": {
      "warmup_itrs": 20,
      "min_bench_itrs": 373,
      "min_bench_time": 0,
      "estimated_time": 0
    },
    "30k_ifelse": {
      "warmup_itrs": 20,
      "min_bench_itrs": 56,
      "min_bench_time": 0,
      "estimated_time": 0
    },
    "cfunc_itself": {
      "warmup_itrs": 20,
      "min_bench_itrs": 449,
      "min_bench_time": 0,
      "estimated_time": 0
    },
    "respond_to": {
      "warmup_itrs": 20,
      "min_bench_itrs": 108,
      "min_bench_time": 0,
      "estimated_time": 0
    },
    "getivar": {
      "warmup_itrs": 20,
      "min_bench_itrs": 786,
      "min_bench_time": 0,
      "estimated_time": 0
    },
    "nbody": {
      "warmup_itrs": 20,
      "min_bench_itrs": 275,
      "min_bench_time": 0,
      "estimated_time": 0
    },
    "erubi_rails": {
      "warmup_itrs": 20,
      "min_bench_itrs": 982,
      "min_bench_time": 0,
      "estimated_time": 0
    },
    "erubi": {
      "warmup_itrs": 20,
      "min_bench_itrs": 47,
      "min_bench_time": 0,
      "estimated_time": 0
    }
  },
  "yjit_stats": {
    "fib": {
      "warmup_itrs": 20,
      "min_bench_itrs": 319,
      "min_bench_time": 0,
      "estimated_time": 0
    },
    "30k_methods": {
      "warmup_itrs": 20,
      "min_bench_itrs": 22,
      "min_bench_time": 0,
      "estimated_time": 0
    },
    "liquid-render": {
      "warmup_itrs": 20,
      "min_bench_itrs": 156,
      "min_bench_time": 0,
      "estimated_time": 0
    },
    "activerecord": {
      "warmup_itrs": 20,
      "min_bench_itrs": 184,
      "min_bench_time": 0,
      "estimated_time": 0
    },
    "binarytrees": {
      "warmup_itrs": 20,
      "min_bench_itrs": 63,
      "min_bench_time": 0,
      "estimated_time": 0
    },
    "discourse": {
      "warmup_itrs": 20,
      "min_bench_itrs": 38,
      "min_bench_time": 0,
      "estimated_time": 0
    },
    "rubykon": {
      "warmup_itrs": 20,
      "min_bench_itrs": 15,
      "min_bench_time": 0,
      "estimated_time": 0
    },
    "psych-load": {
      "warmup_itrs": 20,
      "min_bench_itrs": 15,
      "min_bench_time": 0,
      "estimated_time": 0
    },
    "hexapdf": {
      "warmup_itrs": 20,
      "min_bench_itrs": 15,
      "min_bench_time": 0,
      "estimated_time": 0
    },
    "optcarrot": {
      "warmup_itrs": 20,
      "min_bench_itrs": 15,
      "min_bench_time": 0,
      "estimated_time": 0
    },
    "setivar": {
      "warmup_itrs": 20,
      "min_bench_itrs": 1902,
      "min_bench_time": 0,
      "estimated_time": 0
    },
    "lee": {
      "warmup_itrs": 20,
      "min_bench_itrs": 21,
      "min_bench_time": 0,
      "estimated_time": 0
    },
    "chunky_png": {
      "warmup_itrs": 20,
      "min_bench_itrs": 30,
      "min_bench_time": 0,
      "estimated_time": 0
    },
    "fannkuchredux": {
      "warmup_itrs": 20,
      "min_bench_itrs": 15,
      "min_bench_time": 0,
      "estimated_time": 0
    },
    "mail": {
      "warmup_itrs": 20,
      "min_bench_itrs": 123,
      "min_bench_time": 0,
      "estimated_time": 0
    },
    "railsbench": {
      "warmup_itrs": 20,
      "min_bench_itrs": 15,
      "min_bench_time": 0,
      "estimated_time": 0
    },
    "keyword_args": {
      "warmup_itrs": 20,
      "min_bench_itrs": 373,
      "min_bench_time": 0,
      "estimated_time": 0
    },
    "30k_ifelse": {
      "warmup_itrs": 20,
      "min_bench_itrs": 56,
      "min_bench_time": 0,
      "estimated_time": 0
    },
    "cfunc_itself": {
      "warmup_itrs": 20,
      "min_bench_itrs": 449,
      "min_bench_time": 0,
      "estimated_time": 0
    },
    "respond_to": {
      "warmup_itrs": 20,
      "min_bench_itrs": 108,
      "min_bench_time": 0,
      "estimated_time": 0
    },
    "getivar": {
      "warmup_itrs": 20,
      "min_bench_itrs": 786,
      "min_bench_time": 0,
      "estimated_time": 0
    },
    "nbody": {
      "warmup_itrs": 20,
      "min_bench_itrs": 275,
      "min_bench_time": 0,
      "estimated_time": 0
    },
    "erubi_rails": {
      "warmup_itrs": 20,
      "min_bench_itrs": 982,
      "min_bench_time": 0,
      "estimated_time": 0
    },
    "erubi": {
      "warmup_itrs": 20,
      "min_bench_itrs": 47,
      "min_bench_time": 0,
      "estimated_time": 0
    }
  },
  "estimated_time": 8011
}
